{
  "generated_at": "2026-03-13T11:19:40Z",
  "repo_root": "/Users/bpds/Documents/Entrepot/Git/Compilons/videosteno/organic-programming",
  "timeout": "10s",
  "dry_run": true,
  "summary": {
    "discovered": 102,
    "selected": 102,
    "assemblies": 66,
    "compositions": 36,
    "dry_run": 102,
    "skipped": 0,
    "passed": 0,
    "smoke_passed": 0,
    "build_failed": 0,
    "run_failed": 0,
    "timed_out": 0
  },
  "results": [
    {
      "name": "gudule-greeting-c-web",
      "path": "recipes/assemblies/gudule-greeting-c-web",
      "family_name": "Greeting-C-Web",
      "display_family": "Greeting-C-Web (Web UI)",
      "display_name": "Gudule Greeting-C-Web (Web UI)",
      "kind": "assembly",
      "status": "dry-run",
      "validation": "launch-smoke",
      "transport": "tcp",
      "platforms": [
        "macos"
      ],
      "requires": [
        "cmake",
        "make",
        "node",
        "npm",
        "protoc"
      ]
    },
    {
      "name": "gudule-greeting-cpp-web",
      "path": "recipes/assemblies/gudule-greeting-cpp-web",
      "family_name": "Greeting-Cpp-Web",
      "display_family": "Greeting-Cpp-Web (Web UI)",
      "display_name": "Gudule Greeting-Cpp-Web (Web UI)",
      "kind": "assembly",
      "status": "dry-run",
      "validation": "launch-smoke",
      "transport": "tcp",
      "platforms": [
        "macos"
      ],
      "requires": [
        "cmake",
        "make",
        "node",
        "npm",
        "protoc"
      ]
    },
    {
      "name": "gudule-greeting-csharp-web",
      "path": "recipes/assemblies/gudule-greeting-csharp-web",
      "family_name": "Greeting-Csharp-Web",
      "display_family": "Greeting-Csharp-Web (Web UI)",
      "display_name": "Gudule Greeting-Csharp-Web (Web UI)",
      "kind": "assembly",
      "status": "dry-run",
      "validation": "launch-smoke",
      "transport": "tcp",
      "platforms": [
        "macos"
      ],
      "requires": [
        "dotnet",
        "node",
        "npm",
        "protoc"
      ]
    },
    {
      "name": "gudule-greeting-dart-web",
      "path": "recipes/assemblies/gudule-greeting-dart-web",
      "family_name": "Greeting-Dart-Web",
      "display_family": "Greeting-Dart-Web (Web UI)",
      "display_name": "Gudule Greeting-Dart-Web (Web UI)",
      "kind": "assembly",
      "status": "dry-run",
      "validation": "launch-smoke",
      "transport": "tcp",
      "platforms": [
        "macos"
      ],
      "requires": [
        "dart",
        "node",
        "npm",
        "protoc"
      ]
    },
    {
      "name": "gudule-greeting-dotnet-c",
      "path": "recipes/assemblies/gudule-greeting-dotnet-c",
      "family_name": "Greeting-Dotnet-C",
      "display_family": "Greeting-Dotnet-C (.NET UI)",
      "display_name": "Gudule Greeting-Dotnet-C (.NET UI)",
      "kind": "assembly",
      "status": "dry-run",
      "validation": "launch-smoke",
      "transport": "stdio",
      "platforms": [
        "macos"
      ],
      "requires": [
        "cmake",
        "make",
        "dotnet"
      ]
    },
    {
      "name": "gudule-greeting-dotnet-cpp",
      "path": "recipes/assemblies/gudule-greeting-dotnet-cpp",
      "family_name": "Greeting-Dotnet-Cpp",
      "display_family": "Greeting-Dotnet-Cpp (.NET UI)",
      "display_name": "Gudule Greeting-Dotnet-Cpp (.NET UI)",
      "kind": "assembly",
      "status": "dry-run",
      "validation": "launch-smoke",
      "transport": "stdio",
      "platforms": [
        "macos"
      ],
      "requires": [
        "cmake",
        "make",
        "dotnet"
      ]
    },
    {
      "name": "gudule-greeting-dotnet-csharp",
      "path": "recipes/assemblies/gudule-greeting-dotnet-csharp",
      "family_name": "Greeting-Dotnet-Csharp",
      "display_family": "Greeting-Dotnet-Csharp (.NET UI)",
      "display_name": "Gudule Greeting-Dotnet-Csharp (.NET UI)",
      "kind": "assembly",
      "status": "dry-run",
      "validation": "launch-smoke",
      "transport": "stdio",
      "platforms": [
        "macos"
      ],
      "requires": [
        "dotnet"
      ]
    },
    {
      "name": "gudule-greeting-dotnet-dart",
      "path": "recipes/assemblies/gudule-greeting-dotnet-dart",
      "family_name": "Greeting-Dotnet-Dart",
      "display_family": "Greeting-Dotnet-Dart (.NET UI)",
      "display_name": "Gudule Greeting-Dotnet-Dart (.NET UI)",
      "kind": "assembly",
      "status": "dry-run",
      "validation": "launch-smoke",
      "transport": "stdio",
      "platforms": [
        "macos"
      ],
      "requires": [
        "dart",
        "dotnet"
      ]
    },
    {
      "name": "gudule-greeting-dotnet-go",
      "path": "recipes/assemblies/gudule-greeting-dotnet-go",
      "family_name": "Greeting-Dotnet-Go",
      "display_family": "Greeting-Dotnet-Go (.NET UI)",
      "display_name": "Gudule Greeting-Dotnet-Go (.NET UI)",
      "kind": "assembly",
      "status": "dry-run",
      "validation": "launch-smoke",
      "transport": "stdio",
      "platforms": [
        "macos"
      ],
      "requires": [
        "go",
        "dotnet"
      ]
    },
    {
      "name": "gudule-greeting-dotnet-java",
      "path": "recipes/assemblies/gudule-greeting-dotnet-java",
      "family_name": "Greeting-Dotnet-Java",
      "display_family": "Greeting-Dotnet-Java (.NET UI)",
      "display_name": "Gudule Greeting-Dotnet-Java (.NET UI)",
      "kind": "assembly",
      "status": "dry-run",
      "validation": "launch-smoke",
      "transport": "stdio",
      "platforms": [
        "macos"
      ],
      "requires": [
        "gradle",
        "dotnet"
      ]
    },
    {
      "name": "gudule-greeting-dotnet-kotlin",
      "path": "recipes/assemblies/gudule-greeting-dotnet-kotlin",
      "family_name": "Greeting-Dotnet-Kotlin",
      "display_family": "Greeting-Dotnet-Kotlin (.NET UI)",
      "display_name": "Gudule Greeting-Dotnet-Kotlin (.NET UI)",
      "kind": "assembly",
      "status": "dry-run",
      "validation": "launch-smoke",
      "transport": "stdio",
      "platforms": [
        "macos"
      ],
      "requires": [
        "java",
        "dotnet"
      ]
    },
    {
      "name": "gudule-greeting-dotnet-node",
      "path": "recipes/assemblies/gudule-greeting-dotnet-node",
      "family_name": "Greeting-Dotnet-Node",
      "display_family": "Greeting-Dotnet-Node (.NET UI)",
      "display_name": "Gudule Greeting-Dotnet-Node (.NET UI)",
      "kind": "assembly",
      "status": "dry-run",
      "validation": "launch-smoke",
      "transport": "stdio",
      "platforms": [
        "macos"
      ],
      "requires": [
        "node",
        "npm",
        "dotnet"
      ]
    },
    {
      "name": "gudule-greeting-dotnet-python",
      "path": "recipes/assemblies/gudule-greeting-dotnet-python",
      "family_name": "Greeting-Dotnet-Python",
      "display_family": "Greeting-Dotnet-Python (.NET UI)",
      "display_name": "Gudule Greeting-Dotnet-Python (.NET UI)",
      "kind": "assembly",
      "status": "dry-run",
      "validation": "launch-smoke",
      "transport": "stdio",
      "platforms": [
        "macos"
      ],
      "requires": [
        "python3",
        "dotnet"
      ]
    },
    {
      "name": "gudule-greeting-dotnet-rust",
      "path": "recipes/assemblies/gudule-greeting-dotnet-rust",
      "family_name": "Greeting-Dotnet-Rust",
      "display_family": "Greeting-Dotnet-Rust (.NET UI)",
      "display_name": "Gudule Greeting-Dotnet-Rust (.NET UI)",
      "kind": "assembly",
      "status": "dry-run",
      "validation": "launch-smoke",
      "transport": "stdio",
      "platforms": [
        "macos"
      ],
      "requires": [
        "cargo",
        "dotnet"
      ]
    },
    {
      "name": "gudule-greeting-dotnet-swift",
      "path": "recipes/assemblies/gudule-greeting-dotnet-swift",
      "family_name": "Greeting-Dotnet-Swift",
      "display_family": "Greeting-Dotnet-Swift (.NET UI)",
      "display_name": "Gudule Greeting-Dotnet-Swift (.NET UI)",
      "kind": "assembly",
      "status": "dry-run",
      "validation": "launch-smoke",
      "transport": "stdio",
      "platforms": [
        "macos"
      ],
      "requires": [
        "swift",
        "xcodebuild",
        "dotnet"
      ]
    },
    {
      "name": "gudule-greeting-flutter-c",
      "path": "recipes/assemblies/gudule-greeting-flutter-c",
      "family_name": "Greeting-Flutter-C",
      "display_family": "Greeting-Flutter-C (Flutter UI)",
      "display_name": "Gudule Greeting-Flutter-C (Flutter UI)",
      "kind": "assembly",
      "status": "dry-run",
      "validation": "launch-smoke",
      "transport": "stdio",
      "platforms": [
        "macos"
      ],
      "requires": [
        "cmake",
        "make",
        "flutter",
        "dart"
      ]
    },
    {
      "name": "gudule-greeting-flutter-cpp",
      "path": "recipes/assemblies/gudule-greeting-flutter-cpp",
      "family_name": "Greeting-Flutter-Cpp",
      "display_family": "Greeting-Flutter-Cpp (Flutter UI)",
      "display_name": "Gudule Greeting-Flutter-Cpp (Flutter UI)",
      "kind": "assembly",
      "status": "dry-run",
      "validation": "launch-smoke",
      "transport": "stdio",
      "platforms": [
        "macos"
      ],
      "requires": [
        "cmake",
        "make",
        "flutter",
        "dart"
      ]
    },
    {
      "name": "gudule-greeting-flutter-csharp",
      "path": "recipes/assemblies/gudule-greeting-flutter-csharp",
      "family_name": "Greeting-Flutter-Csharp",
      "display_family": "Greeting-Flutter-Csharp (Flutter UI)",
      "display_name": "Gudule Greeting-Flutter-Csharp (Flutter UI)",
      "kind": "assembly",
      "status": "dry-run",
      "validation": "launch-smoke",
      "transport": "stdio",
      "platforms": [
        "macos"
      ],
      "requires": [
        "dotnet",
        "flutter",
        "dart"
      ]
    },
    {
      "name": "gudule-greeting-flutter-dart",
      "path": "recipes/assemblies/gudule-greeting-flutter-dart",
      "family_name": "Greeting-Flutter-Dart",
      "display_family": "Greeting-Flutter-Dart (Flutter UI)",
      "display_name": "Gudule Greeting-Flutter-Dart (Flutter UI)",
      "kind": "assembly",
      "status": "dry-run",
      "validation": "launch-smoke",
      "transport": "stdio",
      "platforms": [
        "macos"
      ],
      "requires": [
        "dart",
        "flutter"
      ]
    },
    {
      "name": "gudule-greeting-flutter-go",
      "path": "recipes/assemblies/gudule-greeting-flutter-go",
      "family_name": "Greeting-Flutter-Go",
      "display_family": "Greeting-Flutter-Go (Flutter UI)",
      "display_name": "Gudule Greeting-Flutter-Go (Flutter UI)",
      "kind": "assembly",
      "status": "dry-run",
      "validation": "launch-smoke",
      "transport": "stdio",
      "platforms": [
        "macos"
      ],
      "requires": [
        "go",
        "flutter",
        "dart"
      ]
    },
    {
      "name": "gudule-greeting-flutter-java",
      "path": "recipes/assemblies/gudule-greeting-flutter-java",
      "family_name": "Greeting-Flutter-Java",
      "display_family": "Greeting-Flutter-Java (Flutter UI)",
      "display_name": "Gudule Greeting-Flutter-Java (Flutter UI)",
      "kind": "assembly",
      "status": "dry-run",
      "validation": "launch-smoke",
      "transport": "stdio",
      "platforms": [
        "macos"
      ],
      "requires": [
        "gradle",
        "flutter",
        "dart"
      ]
    },
    {
      "name": "gudule-greeting-flutter-kotlin",
      "path": "recipes/assemblies/gudule-greeting-flutter-kotlin",
      "family_name": "Greeting-Flutter-Kotlin",
      "display_family": "Greeting-Flutter-Kotlin (Flutter UI)",
      "display_name": "Gudule Greeting-Flutter-Kotlin (Flutter UI)",
      "kind": "assembly",
      "status": "dry-run",
      "validation": "launch-smoke",
      "transport": "stdio",
      "platforms": [
        "macos"
      ],
      "requires": [
        "java",
        "flutter",
        "dart"
      ]
    },
    {
      "name": "gudule-greeting-flutter-node",
      "path": "recipes/assemblies/gudule-greeting-flutter-node",
      "family_name": "Greeting-Flutter-Node",
      "display_family": "Greeting-Flutter-Node (Flutter UI)",
      "display_name": "Gudule Greeting-Flutter-Node (Flutter UI)",
      "kind": "assembly",
      "status": "dry-run",
      "validation": "launch-smoke",
      "transport": "stdio",
      "platforms": [
        "macos"
      ],
      "requires": [
        "node",
        "npm",
        "flutter",
        "dart"
      ]
    },
    {
      "name": "gudule-greeting-flutter-python",
      "path": "recipes/assemblies/gudule-greeting-flutter-python",
      "family_name": "Greeting-Flutter-Python",
      "display_family": "Greeting-Flutter-Python (Flutter UI)",
      "display_name": "Gudule Greeting-Flutter-Python (Flutter UI)",
      "kind": "assembly",
      "status": "dry-run",
      "validation": "launch-smoke",
      "transport": "stdio",
      "platforms": [
        "macos"
      ],
      "requires": [
        "python3",
        "flutter",
        "dart"
      ]
    },
    {
      "name": "gudule-greeting-flutter-rust",
      "path": "recipes/assemblies/gudule-greeting-flutter-rust",
      "family_name": "Greeting-Flutter-Rust",
      "display_family": "Greeting-Flutter-Rust (Flutter UI)",
      "display_name": "Gudule Greeting-Flutter-Rust (Flutter UI)",
      "kind": "assembly",
      "status": "dry-run",
      "validation": "launch-smoke",
      "transport": "stdio",
      "platforms": [
        "macos"
      ],
      "requires": [
        "cargo",
        "flutter",
        "dart"
      ]
    },
    {
      "name": "gudule-greeting-flutter-swift",
      "path": "recipes/assemblies/gudule-greeting-flutter-swift",
      "family_name": "Greeting-Flutter-Swift",
      "display_family": "Greeting-Flutter-Swift (Flutter UI)",
      "display_name": "Gudule Greeting-Flutter-Swift (Flutter UI)",
      "kind": "assembly",
      "status": "dry-run",
      "validation": "launch-smoke",
      "transport": "stdio",
      "platforms": [
        "macos"
      ],
      "requires": [
        "swift",
        "xcodebuild",
        "flutter",
        "dart"
      ]
    },
    {
      "name": "gudule-greeting-go-web",
      "path": "recipes/assemblies/gudule-greeting-go-web",
      "family_name": "Greeting-Go-Web",
      "display_family": "Greeting-Go-Web (Web UI)",
      "display_name": "Gudule Greeting-Go-Web (Web UI)",
      "kind": "assembly",
      "status": "dry-run",
      "validation": "launch-smoke",
      "transport": "tcp",
      "platforms": [
        "macos"
      ],
      "requires": [
        "go",
        "node",
        "npm",
        "protoc"
      ]
    },
    {
      "name": "gudule-greeting-java-web",
      "path": "recipes/assemblies/gudule-greeting-java-web",
      "family_name": "Greeting-Java-Web",
      "display_family": "Greeting-Java-Web (Web UI)",
      "display_name": "Gudule Greeting-Java-Web (Web UI)",
      "kind": "assembly",
      "status": "dry-run",
      "validation": "launch-smoke",
      "transport": "tcp",
      "platforms": [
        "macos"
      ],
      "requires": [
        "gradle",
        "node",
        "npm",
        "protoc"
      ]
    },
    {
      "name": "gudule-greeting-kotlin-web",
      "path": "recipes/assemblies/gudule-greeting-kotlin-web",
      "family_name": "Greeting-Kotlin-Web",
      "display_family": "Greeting-Kotlin-Web (Web UI)",
      "display_name": "Gudule Greeting-Kotlin-Web (Web UI)",
      "kind": "assembly",
      "status": "dry-run",
      "validation": "launch-smoke",
      "transport": "tcp",
      "platforms": [
        "macos"
      ],
      "requires": [
        "java",
        "node",
        "npm",
        "protoc"
      ]
    },
    {
      "name": "gudule-greeting-kotlinui-c",
      "path": "recipes/assemblies/gudule-greeting-kotlinui-c",
      "family_name": "Greeting-Kotlinui-C",
      "display_family": "Greeting-Kotlinui-C (Kotlin UI)",
      "display_name": "Gudule Greeting-Kotlinui-C (Kotlin UI)",
      "kind": "assembly",
      "status": "dry-run",
      "validation": "launch-smoke",
      "transport": "stdio",
      "platforms": [
        "macos"
      ],
      "requires": [
        "cmake",
        "make",
        "java"
      ]
    },
    {
      "name": "gudule-greeting-kotlinui-cpp",
      "path": "recipes/assemblies/gudule-greeting-kotlinui-cpp",
      "family_name": "Greeting-Kotlinui-Cpp",
      "display_family": "Greeting-Kotlinui-Cpp (Kotlin UI)",
      "display_name": "Gudule Greeting-Kotlinui-Cpp (Kotlin UI)",
      "kind": "assembly",
      "status": "dry-run",
      "validation": "launch-smoke",
      "transport": "stdio",
      "platforms": [
        "macos"
      ],
      "requires": [
        "cmake",
        "make",
        "java"
      ]
    },
    {
      "name": "gudule-greeting-kotlinui-csharp",
      "path": "recipes/assemblies/gudule-greeting-kotlinui-csharp",
      "family_name": "Greeting-Kotlinui-Csharp",
      "display_family": "Greeting-Kotlinui-Csharp (Kotlin UI)",
      "display_name": "Gudule Greeting-Kotlinui-Csharp (Kotlin UI)",
      "kind": "assembly",
      "status": "dry-run",
      "validation": "launch-smoke",
      "transport": "stdio",
      "platforms": [
        "macos"
      ],
      "requires": [
        "dotnet",
        "java"
      ]
    },
    {
      "name": "gudule-greeting-kotlinui-dart",
      "path": "recipes/assemblies/gudule-greeting-kotlinui-dart",
      "family_name": "Greeting-Kotlinui-Dart",
      "display_family": "Greeting-Kotlinui-Dart (Kotlin UI)",
      "display_name": "Gudule Greeting-Kotlinui-Dart (Kotlin UI)",
      "kind": "assembly",
      "status": "dry-run",
      "validation": "launch-smoke",
      "transport": "stdio",
      "platforms": [
        "macos"
      ],
      "requires": [
        "dart",
        "java"
      ]
    },
    {
      "name": "gudule-greeting-kotlinui-go",
      "path": "recipes/assemblies/gudule-greeting-kotlinui-go",
      "family_name": "Greeting-Kotlinui-Go",
      "display_family": "Greeting-Kotlinui-Go (Kotlin UI)",
      "display_name": "Gudule Greeting-Kotlinui-Go (Kotlin UI)",
      "kind": "assembly",
      "status": "dry-run",
      "validation": "launch-smoke",
      "transport": "stdio",
      "platforms": [
        "macos"
      ],
      "requires": [
        "go",
        "java"
      ]
    },
    {
      "name": "gudule-greeting-kotlinui-java",
      "path": "recipes/assemblies/gudule-greeting-kotlinui-java",
      "family_name": "Greeting-Kotlinui-Java",
      "display_family": "Greeting-Kotlinui-Java (Kotlin UI)",
      "display_name": "Gudule Greeting-Kotlinui-Java (Kotlin UI)",
      "kind": "assembly",
      "status": "dry-run",
      "validation": "launch-smoke",
      "transport": "stdio",
      "platforms": [
        "macos"
      ],
      "requires": [
        "gradle",
        "java"
      ]
    },
    {
      "name": "gudule-greeting-kotlinui-kotlin",
      "path": "recipes/assemblies/gudule-greeting-kotlinui-kotlin",
      "family_name": "Greeting-Kotlinui-Kotlin",
      "display_family": "Greeting-Kotlinui-Kotlin (Kotlin UI)",
      "display_name": "Gudule Greeting-Kotlinui-Kotlin (Kotlin UI)",
      "kind": "assembly",
      "status": "dry-run",
      "validation": "launch-smoke",
      "transport": "stdio",
      "platforms": [
        "macos"
      ],
      "requires": [
        "java"
      ]
    },
    {
      "name": "gudule-greeting-kotlinui-node",
      "path": "recipes/assemblies/gudule-greeting-kotlinui-node",
      "family_name": "Greeting-Kotlinui-Node",
      "display_family": "Greeting-Kotlinui-Node (Kotlin UI)",
      "display_name": "Gudule Greeting-Kotlinui-Node (Kotlin UI)",
      "kind": "assembly",
      "status": "dry-run",
      "validation": "launch-smoke",
      "transport": "stdio",
      "platforms": [
        "macos"
      ],
      "requires": [
        "node",
        "npm",
        "java"
      ]
    },
    {
      "name": "gudule-greeting-kotlinui-python",
      "path": "recipes/assemblies/gudule-greeting-kotlinui-python",
      "family_name": "Greeting-Kotlinui-Python",
      "display_family": "Greeting-Kotlinui-Python (Kotlin UI)",
      "display_name": "Gudule Greeting-Kotlinui-Python (Kotlin UI)",
      "kind": "assembly",
      "status": "dry-run",
      "validation": "launch-smoke",
      "transport": "stdio",
      "platforms": [
        "macos"
      ],
      "requires": [
        "python3",
        "java"
      ]
    },
    {
      "name": "gudule-greeting-kotlinui-rust",
      "path": "recipes/assemblies/gudule-greeting-kotlinui-rust",
      "family_name": "Greeting-Kotlinui-Rust",
      "display_family": "Greeting-Kotlinui-Rust (Kotlin UI)",
      "display_name": "Gudule Greeting-Kotlinui-Rust (Kotlin UI)",
      "kind": "assembly",
      "status": "dry-run",
      "validation": "launch-smoke",
      "transport": "stdio",
      "platforms": [
        "macos"
      ],
      "requires": [
        "cargo",
        "java"
      ]
    },
    {
      "name": "gudule-greeting-kotlinui-swift",
      "path": "recipes/assemblies/gudule-greeting-kotlinui-swift",
      "family_name": "Greeting-Kotlinui-Swift",
      "display_family": "Greeting-Kotlinui-Swift (Kotlin UI)",
      "display_name": "Gudule Greeting-Kotlinui-Swift (Kotlin UI)",
      "kind": "assembly",
      "status": "dry-run",
      "validation": "launch-smoke",
      "transport": "stdio",
      "platforms": [
        "macos"
      ],
      "requires": [
        "swift",
        "xcodebuild",
        "java"
      ]
    },
    {
      "name": "gudule-greeting-node-web",
      "path": "recipes/assemblies/gudule-greeting-node-web",
      "family_name": "Greeting-Node-Web",
      "display_family": "Greeting-Node-Web (Web UI)",
      "display_name": "Gudule Greeting-Node-Web (Web UI)",
      "kind": "assembly",
      "status": "dry-run",
      "validation": "launch-smoke",
      "transport": "tcp",
      "platforms": [
        "macos"
      ],
      "requires": [
        "node",
        "npm",
        "protoc"
      ]
    },
    {
      "name": "gudule-greeting-python-web",
      "path": "recipes/assemblies/gudule-greeting-python-web",
      "family_name": "Greeting-Python-Web",
      "display_family": "Greeting-Python-Web (Web UI)",
      "display_name": "Gudule Greeting-Python-Web (Web UI)",
      "kind": "assembly",
      "status": "dry-run",
      "validation": "launch-smoke",
      "transport": "tcp",
      "platforms": [
        "macos"
      ],
      "requires": [
        "python3",
        "node",
        "npm",
        "protoc"
      ]
    },
    {
      "name": "gudule-greeting-qt-c",
      "path": "recipes/assemblies/gudule-greeting-qt-c",
      "family_name": "Greeting-Qt-C",
      "display_family": "Greeting-Qt-C (Qt UI)",
      "display_name": "Gudule Greeting-Qt-C (Qt UI)",
      "kind": "assembly",
      "status": "dry-run",
      "validation": "launch-smoke",
      "transport": "stdio",
      "platforms": [
        "macos"
      ],
      "requires": [
        "cmake",
        "make"
      ]
    },
    {
      "name": "gudule-greeting-qt-cpp",
      "path": "recipes/assemblies/gudule-greeting-qt-cpp",
      "family_name": "Greeting-Qt-Cpp",
      "display_family": "Greeting-Qt-Cpp (Qt UI)",
      "display_name": "Gudule Greeting-Qt-Cpp (Qt UI)",
      "kind": "assembly",
      "status": "dry-run",
      "validation": "launch-smoke",
      "transport": "stdio",
      "platforms": [
        "macos"
      ],
      "requires": [
        "cmake",
        "make"
      ]
    },
    {
      "name": "gudule-greeting-qt-csharp",
      "path": "recipes/assemblies/gudule-greeting-qt-csharp",
      "family_name": "Greeting-Qt-Csharp",
      "display_family": "Greeting-Qt-Csharp (Qt UI)",
      "display_name": "Gudule Greeting-Qt-Csharp (Qt UI)",
      "kind": "assembly",
      "status": "dry-run",
      "validation": "launch-smoke",
      "transport": "stdio",
      "platforms": [
        "macos"
      ],
      "requires": [
        "dotnet",
        "cmake"
      ]
    },
    {
      "name": "gudule-greeting-qt-dart",
      "path": "recipes/assemblies/gudule-greeting-qt-dart",
      "family_name": "Greeting-Qt-Dart",
      "display_family": "Greeting-Qt-Dart (Qt UI)",
      "display_name": "Gudule Greeting-Qt-Dart (Qt UI)",
      "kind": "assembly",
      "status": "dry-run",
      "validation": "launch-smoke",
      "transport": "stdio",
      "platforms": [
        "macos"
      ],
      "requires": [
        "dart",
        "cmake"
      ]
    },
    {
      "name": "gudule-greeting-qt-go",
      "path": "recipes/assemblies/gudule-greeting-qt-go",
      "family_name": "Greeting-Qt-Go",
      "display_family": "Greeting-Qt-Go (Qt UI)",
      "display_name": "Gudule Greeting-Qt-Go (Qt UI)",
      "kind": "assembly",
      "status": "dry-run",
      "validation": "launch-smoke",
      "transport": "stdio",
      "platforms": [
        "macos"
      ],
      "requires": [
        "go",
        "cmake"
      ]
    },
    {
      "name": "gudule-greeting-qt-java",
      "path": "recipes/assemblies/gudule-greeting-qt-java",
      "family_name": "Greeting-Qt-Java",
      "display_family": "Greeting-Qt-Java (Qt UI)",
      "display_name": "Gudule Greeting-Qt-Java (Qt UI)",
      "kind": "assembly",
      "status": "dry-run",
      "validation": "launch-smoke",
      "transport": "stdio",
      "platforms": [
        "macos"
      ],
      "requires": [
        "gradle"
      ]
    },
    {
      "name": "gudule-greeting-qt-kotlin",
      "path": "recipes/assemblies/gudule-greeting-qt-kotlin",
      "family_name": "Greeting-Qt-Kotlin",
      "display_family": "Greeting-Qt-Kotlin (Qt UI)",
      "display_name": "Gudule Greeting-Qt-Kotlin (Qt UI)",
      "kind": "assembly",
      "status": "dry-run",
      "validation": "launch-smoke",
      "transport": "stdio",
      "platforms": [
        "macos"
      ],
      "requires": [
        "java",
        "cmake"
      ]
    },
    {
      "name": "gudule-greeting-qt-node",
      "path": "recipes/assemblies/gudule-greeting-qt-node",
      "family_name": "Greeting-Qt-Node",
      "display_family": "Greeting-Qt-Node (Qt UI)",
      "display_name": "Gudule Greeting-Qt-Node (Qt UI)",
      "kind": "assembly",
      "status": "dry-run",
      "validation": "launch-smoke",
      "transport": "stdio",
      "platforms": [
        "macos"
      ],
      "requires": [
        "node",
        "npm",
        "cmake"
      ]
    },
    {
      "name": "gudule-greeting-qt-python",
      "path": "recipes/assemblies/gudule-greeting-qt-python",
      "family_name": "Greeting-Qt-Python",
      "display_family": "Greeting-Qt-Python (Qt UI)",
      "display_name": "Gudule Greeting-Qt-Python (Qt UI)",
      "kind": "assembly",
      "status": "dry-run",
      "validation": "launch-smoke",
      "transport": "stdio",
      "platforms": [
        "macos"
      ],
      "requires": [
        "python3",
        "cmake"
      ]
    },
    {
      "name": "gudule-greeting-qt-rust",
      "path": "recipes/assemblies/gudule-greeting-qt-rust",
      "family_name": "Greeting-Qt-Rust",
      "display_family": "Greeting-Qt-Rust (Qt UI)",
      "display_name": "Gudule Greeting-Qt-Rust (Qt UI)",
      "kind": "assembly",
      "status": "dry-run",
      "validation": "launch-smoke",
      "transport": "stdio",
      "platforms": [
        "macos"
      ],
      "requires": [
        "cargo",
        "cmake"
      ]
    },
    {
      "name": "gudule-greeting-qt-swift",
      "path": "recipes/assemblies/gudule-greeting-qt-swift",
      "family_name": "Greeting-Qt-Swift",
      "display_family": "Greeting-Qt-Swift (Qt UI)",
      "display_name": "Gudule Greeting-Qt-Swift (Qt UI)",
      "kind": "assembly",
      "status": "dry-run",
      "validation": "launch-smoke",
      "transport": "stdio",
      "platforms": [
        "macos"
      ],
      "requires": [
        "swift",
        "xcodebuild",
        "cmake"
      ]
    },
    {
      "name": "gudule-greeting-rust-web",
      "path": "recipes/assemblies/gudule-greeting-rust-web",
      "family_name": "Greeting-Rust-Web",
      "display_family": "Greeting-Rust-Web (Web UI)",
      "display_name": "Gudule Greeting-Rust-Web (Web UI)",
      "kind": "assembly",
      "status": "dry-run",
      "validation": "launch-smoke",
      "transport": "tcp",
      "platforms": [
        "macos"
      ],
      "requires": [
        "cargo",
        "node",
        "npm",
        "protoc"
      ]
    },
    {
      "name": "gudule-greeting-swift-web",
      "path": "recipes/assemblies/gudule-greeting-swift-web",
      "family_name": "Greeting-Swift-Web",
      "display_family": "Greeting-Swift-Web (Web UI)",
      "display_name": "Gudule Greeting-Swift-Web (Web UI)",
      "kind": "assembly",
      "status": "dry-run",
      "validation": "launch-smoke",
      "transport": "tcp",
      "platforms": [
        "macos"
      ],
      "requires": [
        "swift",
        "xcodebuild",
        "node",
        "npm",
        "protoc"
      ]
    },
    {
      "name": "gudule-greeting-swiftui-c",
      "path": "recipes/assemblies/gudule-greeting-swiftui-c",
      "family_name": "Greeting-Swiftui-C",
      "display_family": "Greeting-Swiftui-C (SwiftUI)",
      "display_name": "Gudule Greeting-Swiftui-C (SwiftUI)",
      "kind": "assembly",
      "status": "dry-run",
      "validation": "launch-smoke",
      "transport": "stdio",
      "platforms": [
        "macos"
      ],
      "requires": [
        "cmake",
        "make",
        "xcodebuild"
      ]
    },
    {
      "name": "gudule-greeting-swiftui-cpp",
      "path": "recipes/assemblies/gudule-greeting-swiftui-cpp",
      "family_name": "Greeting-Swiftui-Cpp",
      "display_family": "Greeting-Swiftui-Cpp (SwiftUI)",
      "display_name": "Gudule Greeting-Swiftui-Cpp (SwiftUI)",
      "kind": "assembly",
      "status": "dry-run",
      "validation": "launch-smoke",
      "transport": "stdio",
      "platforms": [
        "macos"
      ],
      "requires": [
        "cmake",
        "make",
        "xcodebuild"
      ]
    },
    {
      "name": "gudule-greeting-swiftui-csharp",
      "path": "recipes/assemblies/gudule-greeting-swiftui-csharp",
      "family_name": "Greeting-Swiftui-Csharp",
      "display_family": "Greeting-Swiftui-Csharp (SwiftUI)",
      "display_name": "Gudule Greeting-Swiftui-Csharp (SwiftUI)",
      "kind": "assembly",
      "status": "dry-run",
      "validation": "launch-smoke",
      "transport": "stdio",
      "platforms": [
        "macos"
      ],
      "requires": [
        "dotnet",
        "xcodebuild"
      ]
    },
    {
      "name": "gudule-greeting-swiftui-dart",
      "path": "recipes/assemblies/gudule-greeting-swiftui-dart",
      "family_name": "Greeting-Swiftui-Dart",
      "display_family": "Greeting-Swiftui-Dart (SwiftUI)",
      "display_name": "Gudule Greeting-Swiftui-Dart (SwiftUI)",
      "kind": "assembly",
      "status": "dry-run",
      "validation": "launch-smoke",
      "transport": "stdio",
      "platforms": [
        "macos"
      ],
      "requires": [
        "dart",
        "xcodebuild"
      ]
    },
    {
      "name": "gudule-greeting-swiftui-go",
      "path": "recipes/assemblies/gudule-greeting-swiftui-go",
      "family_name": "Greeting-Swiftui-Go",
      "display_family": "Greeting-Swiftui-Go (SwiftUI)",
      "display_name": "Gudule Greeting-Swiftui-Go (SwiftUI)",
      "kind": "assembly",
      "status": "dry-run",
      "validation": "launch-smoke",
      "transport": "stdio",
      "platforms": [
        "macos"
      ],
      "requires": [
        "go",
        "xcodebuild"
      ]
    },
    {
      "name": "gudule-greeting-swiftui-java",
      "path": "recipes/assemblies/gudule-greeting-swiftui-java",
      "family_name": "Greeting-Swiftui-Java",
      "display_family": "Greeting-Swiftui-Java (SwiftUI)",
      "display_name": "Gudule Greeting-Swiftui-Java (SwiftUI)",
      "kind": "assembly",
      "status": "dry-run",
      "validation": "launch-smoke",
      "transport": "stdio",
      "platforms": [
        "macos"
      ],
      "requires": [
        "gradle",
        "xcodebuild"
      ]
    },
    {
      "name": "gudule-greeting-swiftui-kotlin",
      "path": "recipes/assemblies/gudule-greeting-swiftui-kotlin",
      "family_name": "Greeting-Swiftui-Kotlin",
      "display_family": "Greeting-Swiftui-Kotlin (SwiftUI)",
      "display_name": "Gudule Greeting-Swiftui-Kotlin (SwiftUI)",
      "kind": "assembly",
      "status": "dry-run",
      "validation": "launch-smoke",
      "transport": "stdio",
      "platforms": [
        "macos"
      ],
      "requires": [
        "java",
        "xcodebuild"
      ]
    },
    {
      "name": "gudule-greeting-swiftui-node",
      "path": "recipes/assemblies/gudule-greeting-swiftui-node",
      "family_name": "Greeting-Swiftui-Node",
      "display_family": "Greeting-Swiftui-Node (SwiftUI)",
      "display_name": "Gudule Greeting-Swiftui-Node (SwiftUI)",
      "kind": "assembly",
      "status": "dry-run",
      "validation": "launch-smoke",
      "transport": "stdio",
      "platforms": [
        "macos"
      ],
      "requires": [
        "node",
        "npm",
        "xcodebuild"
      ]
    },
    {
      "name": "gudule-greeting-swiftui-python",
      "path": "recipes/assemblies/gudule-greeting-swiftui-python",
      "family_name": "Greeting-Swiftui-Python",
      "display_family": "Greeting-Swiftui-Python (SwiftUI)",
      "display_name": "Gudule Greeting-Swiftui-Python (SwiftUI)",
      "kind": "assembly",
      "status": "dry-run",
      "validation": "launch-smoke",
      "transport": "stdio",
      "platforms": [
        "macos"
      ],
      "requires": [
        "python3",
        "xcodebuild"
      ]
    },
    {
      "name": "gudule-greeting-swiftui-rust",
      "path": "recipes/assemblies/gudule-greeting-swiftui-rust",
      "family_name": "Greeting-Swiftui-Rust",
      "display_family": "Greeting-Swiftui-Rust (SwiftUI)",
      "display_name": "Gudule Greeting-Swiftui-Rust (SwiftUI)",
      "kind": "assembly",
      "status": "dry-run",
      "validation": "launch-smoke",
      "transport": "stdio",
      "platforms": [
        "macos"
      ],
      "requires": [
        "cargo",
        "xcodebuild"
      ]
    },
    {
      "name": "gudule-greeting-swiftui-swift",
      "path": "recipes/assemblies/gudule-greeting-swiftui-swift",
      "family_name": "Greeting-Swiftui-Swift",
      "display_family": "Greeting-Swiftui-Swift (SwiftUI)",
      "display_name": "Gudule Greeting-Swiftui-Swift (SwiftUI)",
      "kind": "assembly",
      "status": "dry-run",
      "validation": "launch-smoke",
      "transport": "stdio",
      "platforms": [
        "macos"
      ],
      "requires": [
        "swift",
        "xcodebuild"
      ]
    },
    {
      "name": "charon-direct-c-go",
      "path": "recipes/composition/direct-call/charon-direct-c-go",
      "family_name": "Composition-Direct-C-Go",
      "display_family": "Composition-Direct-C-Go",
      "display_name": "Composition-Direct-C-Go",
      "kind": "composition",
      "status": "dry-run",
      "validation": "json-output",
      "platforms": [
        "macos"
      ],
      "requires": [
        "go",
        "op",
        "cmake"
      ]
    },
    {
      "name": "charon-direct-cpp-go",
      "path": "recipes/composition/direct-call/charon-direct-cpp-go",
      "family_name": "Composition-Direct-Cpp-Go",
      "display_family": "Composition-Direct-Cpp-Go",
      "display_name": "Composition-Direct-Cpp-Go",
      "kind": "composition",
      "status": "dry-run",
      "validation": "json-output",
      "platforms": [
        "macos"
      ],
      "requires": [
        "go",
        "op",
        "cmake"
      ]
    },
    {
      "name": "charon-direct-csharp-go",
      "path": "recipes/composition/direct-call/charon-direct-csharp-go",
      "family_name": "Composition-Direct-Csharp-Go",
      "display_family": "Composition-Direct-Csharp-Go",
      "display_name": "Composition-Direct-Csharp-Go",
      "kind": "composition",
      "status": "dry-run",
      "validation": "json-output",
      "platforms": [
        "macos"
      ],
      "requires": [
        "go",
        "op",
        "dotnet"
      ]
    },
    {
      "name": "charon-direct-dart-go",
      "path": "recipes/composition/direct-call/charon-direct-dart-go",
      "family_name": "Composition-Direct-Dart-Go",
      "display_family": "Composition-Direct-Dart-Go",
      "display_name": "Composition-Direct-Dart-Go",
      "kind": "composition",
      "status": "dry-run",
      "validation": "json-output",
      "platforms": [
        "macos"
      ],
      "requires": [
        "go",
        "op",
        "dart"
      ]
    },
    {
      "name": "charon-direct-go-go",
      "path": "recipes/composition/direct-call/charon-direct-go-go",
      "family_name": "Composition-Direct-Go-Go",
      "display_family": "Composition-Direct-Go-Go",
      "display_name": "Composition-Direct-Go-Go",
      "kind": "composition",
      "status": "dry-run",
      "validation": "json-output",
      "platforms": [
        "macos"
      ],
      "requires": [
        "go",
        "op"
      ]
    },
    {
      "name": "charon-direct-java-go",
      "path": "recipes/composition/direct-call/charon-direct-java-go",
      "family_name": "Composition-Direct-Java-Go",
      "display_family": "Composition-Direct-Java-Go",
      "display_name": "Composition-Direct-Java-Go",
      "kind": "composition",
      "status": "dry-run",
      "validation": "json-output",
      "platforms": [
        "macos"
      ],
      "requires": [
        "go",
        "op",
        "java",
        "gradle"
      ]
    },
    {
      "name": "charon-direct-kotlin-go",
      "path": "recipes/composition/direct-call/charon-direct-kotlin-go",
      "family_name": "Composition-Direct-Kotlin-Go",
      "display_family": "Composition-Direct-Kotlin-Go",
      "display_name": "Composition-Direct-Kotlin-Go",
      "kind": "composition",
      "status": "dry-run",
      "validation": "json-output",
      "platforms": [
        "macos"
      ],
      "requires": [
        "go",
        "op",
        "java",
        "gradle"
      ]
    },
    {
      "name": "charon-direct-node-go",
      "path": "recipes/composition/direct-call/charon-direct-node-go",
      "family_name": "Composition-Direct-Node-Go",
      "display_family": "Composition-Direct-Node-Go",
      "display_name": "Composition-Direct-Node-Go",
      "kind": "composition",
      "status": "dry-run",
      "validation": "json-output",
      "platforms": [
        "macos"
      ],
      "requires": [
        "go",
        "op",
        "node",
        "npm"
      ]
    },
    {
      "name": "charon-direct-python-go",
      "path": "recipes/composition/direct-call/charon-direct-python-go",
      "family_name": "Composition-Direct-Python-Go",
      "display_family": "Composition-Direct-Python-Go",
      "display_name": "Composition-Direct-Python-Go",
      "kind": "composition",
      "status": "dry-run",
      "validation": "json-output",
      "platforms": [
        "macos"
      ],
      "requires": [
        "go",
        "op",
        "python3"
      ]
    },
    {
      "name": "charon-direct-ruby-go",
      "path": "recipes/composition/direct-call/charon-direct-ruby-go",
      "family_name": "Composition-Direct-Ruby-Go",
      "display_family": "Composition-Direct-Ruby-Go",
      "display_name": "Composition-Direct-Ruby-Go",
      "kind": "composition",
      "status": "dry-run",
      "validation": "json-output",
      "platforms": [
        "macos"
      ],
      "requires": [
        "go",
        "op",
        "ruby",
        "bundle"
      ]
    },
    {
      "name": "charon-direct-rust-go",
      "path": "recipes/composition/direct-call/charon-direct-rust-go",
      "family_name": "Composition-Direct-Rust-Go",
      "display_family": "Composition-Direct-Rust-Go",
      "display_name": "Composition-Direct-Rust-Go",
      "kind": "composition",
      "status": "dry-run",
      "validation": "json-output",
      "platforms": [
        "macos"
      ],
      "requires": [
        "go",
        "op",
        "cargo"
      ]
    },
    {
      "name": "charon-direct-swift-go",
      "path": "recipes/composition/direct-call/charon-direct-swift-go",
      "family_name": "Composition-Direct-Swift-Go",
      "display_family": "Composition-Direct-Swift-Go",
      "display_name": "Composition-Direct-Swift-Go",
      "kind": "composition",
      "status": "dry-run",
      "validation": "json-output",
      "platforms": [
        "macos"
      ],
      "requires": [
        "go",
        "op",
        "swift",
        "xcodebuild"
      ]
    },
    {
      "name": "charon-fanout-c-go",
      "path": "recipes/composition/fan-out/charon-fanout-c-go",
      "family_name": "Composition-Fanout-C-Go",
      "display_family": "Composition-Fanout-C-Go",
      "display_name": "Composition-Fanout-C-Go",
      "kind": "composition",
      "status": "dry-run",
      "validation": "json-output",
      "platforms": [
        "macos"
      ],
      "requires": [
        "go",
        "op",
        "cmake"
      ]
    },
    {
      "name": "charon-fanout-cpp-go",
      "path": "recipes/composition/fan-out/charon-fanout-cpp-go",
      "family_name": "Composition-Fanout-Cpp-Go",
      "display_family": "Composition-Fanout-Cpp-Go",
      "display_name": "Composition-Fanout-Cpp-Go",
      "kind": "composition",
      "status": "dry-run",
      "validation": "json-output",
      "platforms": [
        "macos"
      ],
      "requires": [
        "go",
        "op",
        "cmake"
      ]
    },
    {
      "name": "charon-fanout-csharp-go",
      "path": "recipes/composition/fan-out/charon-fanout-csharp-go",
      "family_name": "Composition-Fanout-Csharp-Go",
      "display_family": "Composition-Fanout-Csharp-Go",
      "display_name": "Composition-Fanout-Csharp-Go",
      "kind": "composition",
      "status": "dry-run",
      "validation": "json-output",
      "platforms": [
        "macos"
      ],
      "requires": [
        "go",
        "op",
        "dotnet"
      ]
    },
    {
      "name": "charon-fanout-dart-go",
      "path": "recipes/composition/fan-out/charon-fanout-dart-go",
      "family_name": "Composition-Fanout-Dart-Go",
      "display_family": "Composition-Fanout-Dart-Go",
      "display_name": "Composition-Fanout-Dart-Go",
      "kind": "composition",
      "status": "dry-run",
      "validation": "json-output",
      "platforms": [
        "macos"
      ],
      "requires": [
        "go",
        "op",
        "dart"
      ]
    },
    {
      "name": "charon-fanout-go-go",
      "path": "recipes/composition/fan-out/charon-fanout-go-go",
      "family_name": "Composition-Fanout-Go-Go",
      "display_family": "Composition-Fanout-Go-Go",
      "display_name": "Composition-Fanout-Go-Go",
      "kind": "composition",
      "status": "dry-run",
      "validation": "json-output",
      "platforms": [
        "macos"
      ],
      "requires": [
        "go",
        "op"
      ]
    },
    {
      "name": "charon-fanout-java-go",
      "path": "recipes/composition/fan-out/charon-fanout-java-go",
      "family_name": "Composition-Fanout-Java-Go",
      "display_family": "Composition-Fanout-Java-Go",
      "display_name": "Composition-Fanout-Java-Go",
      "kind": "composition",
      "status": "dry-run",
      "validation": "json-output",
      "platforms": [
        "macos"
      ],
      "requires": [
        "go",
        "op",
        "java",
        "gradle"
      ]
    },
    {
      "name": "charon-fanout-kotlin-go",
      "path": "recipes/composition/fan-out/charon-fanout-kotlin-go",
      "family_name": "Composition-Fanout-Kotlin-Go",
      "display_family": "Composition-Fanout-Kotlin-Go",
      "display_name": "Composition-Fanout-Kotlin-Go",
      "kind": "composition",
      "status": "dry-run",
      "validation": "json-output",
      "platforms": [
        "macos"
      ],
      "requires": [
        "go",
        "op",
        "java",
        "gradle"
      ]
    },
    {
      "name": "charon-fanout-node-go",
      "path": "recipes/composition/fan-out/charon-fanout-node-go",
      "family_name": "Composition-Fanout-Node-Go",
      "display_family": "Composition-Fanout-Node-Go",
      "display_name": "Composition-Fanout-Node-Go",
      "kind": "composition",
      "status": "dry-run",
      "validation": "json-output",
      "platforms": [
        "macos"
      ],
      "requires": [
        "go",
        "op",
        "node",
        "npm"
      ]
    },
    {
      "name": "charon-fanout-python-go",
      "path": "recipes/composition/fan-out/charon-fanout-python-go",
      "family_name": "Composition-Fanout-Python-Go",
      "display_family": "Composition-Fanout-Python-Go",
      "display_name": "Composition-Fanout-Python-Go",
      "kind": "composition",
      "status": "dry-run",
      "validation": "json-output",
      "platforms": [
        "macos"
      ],
      "requires": [
        "go",
        "op",
        "python3"
      ]
    },
    {
      "name": "charon-fanout-ruby-go",
      "path": "recipes/composition/fan-out/charon-fanout-ruby-go",
      "family_name": "Composition-Fanout-Ruby-Go",
      "display_family": "Composition-Fanout-Ruby-Go",
      "display_name": "Composition-Fanout-Ruby-Go",
      "kind": "composition",
      "status": "dry-run",
      "validation": "json-output",
      "platforms": [
        "macos"
      ],
      "requires": [
        "go",
        "op",
        "ruby",
        "bundle"
      ]
    },
    {
      "name": "charon-fanout-rust-go",
      "path": "recipes/composition/fan-out/charon-fanout-rust-go",
      "family_name": "Composition-Fanout-Rust-Go",
      "display_family": "Composition-Fanout-Rust-Go",
      "display_name": "Composition-Fanout-Rust-Go",
      "kind": "composition",
      "status": "dry-run",
      "validation": "json-output",
      "platforms": [
        "macos"
      ],
      "requires": [
        "go",
        "op",
        "cargo"
      ]
    },
    {
      "name": "charon-fanout-swift-go",
      "path": "recipes/composition/fan-out/charon-fanout-swift-go",
      "family_name": "Composition-Fanout-Swift-Go",
      "display_family": "Composition-Fanout-Swift-Go",
      "display_name": "Composition-Fanout-Swift-Go",
      "kind": "composition",
      "status": "dry-run",
      "validation": "json-output",
      "platforms": [
        "macos"
      ],
      "requires": [
        "go",
        "op",
        "swift",
        "xcodebuild"
      ]
    },
    {
      "name": "charon-pipeline-c-go",
      "path": "recipes/composition/pipeline/charon-pipeline-c-go",
      "family_name": "Composition-Pipeline-C-Go",
      "display_family": "Composition-Pipeline-C-Go",
      "display_name": "Composition-Pipeline-C-Go",
      "kind": "composition",
      "status": "dry-run",
      "validation": "json-output",
      "platforms": [
        "macos"
      ],
      "requires": [
        "go",
        "op",
        "cmake"
      ]
    },
    {
      "name": "charon-pipeline-cpp-go",
      "path": "recipes/composition/pipeline/charon-pipeline-cpp-go",
      "family_name": "Composition-Pipeline-Cpp-Go",
      "display_family": "Composition-Pipeline-Cpp-Go",
      "display_name": "Composition-Pipeline-Cpp-Go",
      "kind": "composition",
      "status": "dry-run",
      "validation": "json-output",
      "platforms": [
        "macos"
      ],
      "requires": [
        "go",
        "op",
        "cmake"
      ]
    },
    {
      "name": "charon-pipeline-csharp-go",
      "path": "recipes/composition/pipeline/charon-pipeline-csharp-go",
      "family_name": "Composition-Pipeline-Csharp-Go",
      "display_family": "Composition-Pipeline-Csharp-Go",
      "display_name": "Composition-Pipeline-Csharp-Go",
      "kind": "composition",
      "status": "dry-run",
      "validation": "json-output",
      "platforms": [
        "macos"
      ],
      "requires": [
        "go",
        "op",
        "dotnet"
      ]
    },
    {
      "name": "charon-pipeline-dart-go",
      "path": "recipes/composition/pipeline/charon-pipeline-dart-go",
      "family_name": "Composition-Pipeline-Dart-Go",
      "display_family": "Composition-Pipeline-Dart-Go",
      "display_name": "Composition-Pipeline-Dart-Go",
      "kind": "composition",
      "status": "dry-run",
      "validation": "json-output",
      "platforms": [
        "macos"
      ],
      "requires": [
        "go",
        "op",
        "dart"
      ]
    },
    {
      "name": "charon-pipeline-go-go",
      "path": "recipes/composition/pipeline/charon-pipeline-go-go",
      "family_name": "Composition-Pipeline-Go-Go",
      "display_family": "Composition-Pipeline-Go-Go",
      "display_name": "Composition-Pipeline-Go-Go",
      "kind": "composition",
      "status": "dry-run",
      "validation": "json-output",
      "platforms": [
        "macos"
      ],
      "requires": [
        "go",
        "op"
      ]
    },
    {
      "name": "charon-pipeline-java-go",
      "path": "recipes/composition/pipeline/charon-pipeline-java-go",
      "family_name": "Composition-Pipeline-Java-Go",
      "display_family": "Composition-Pipeline-Java-Go",
      "display_name": "Composition-Pipeline-Java-Go",
      "kind": "composition",
      "status": "dry-run",
      "validation": "json-output",
      "platforms": [
        "macos"
      ],
      "requires": [
        "go",
        "op",
        "java",
        "gradle"
      ]
    },
    {
      "name": "charon-pipeline-kotlin-go",
      "path": "recipes/composition/pipeline/charon-pipeline-kotlin-go",
      "family_name": "Composition-Pipeline-Kotlin-Go",
      "display_family": "Composition-Pipeline-Kotlin-Go",
      "display_name": "Composition-Pipeline-Kotlin-Go",
      "kind": "composition",
      "status": "dry-run",
      "validation": "json-output",
      "platforms": [
        "macos"
      ],
      "requires": [
        "go",
        "op",
        "java",
        "gradle"
      ]
    },
    {
      "name": "charon-pipeline-node-go",
      "path": "recipes/composition/pipeline/charon-pipeline-node-go",
      "family_name": "Composition-Pipeline-Node-Go",
      "display_family": "Composition-Pipeline-Node-Go",
      "display_name": "Composition-Pipeline-Node-Go",
      "kind": "composition",
      "status": "dry-run",
      "validation": "json-output",
      "platforms": [
        "macos"
      ],
      "requires": [
        "go",
        "op",
        "node",
        "npm"
      ]
    },
    {
      "name": "charon-pipeline-python-go",
      "path": "recipes/composition/pipeline/charon-pipeline-python-go",
      "family_name": "Composition-Pipeline-Python-Go",
      "display_family": "Composition-Pipeline-Python-Go",
      "display_name": "Composition-Pipeline-Python-Go",
      "kind": "composition",
      "status": "dry-run",
      "validation": "json-output",
      "platforms": [
        "macos"
      ],
      "requires": [
        "go",
        "op",
        "python3"
      ]
    },
    {
      "name": "charon-pipeline-ruby-go",
      "path": "recipes/composition/pipeline/charon-pipeline-ruby-go",
      "family_name": "Composition-Pipeline-Ruby-Go",
      "display_family": "Composition-Pipeline-Ruby-Go",
      "display_name": "Composition-Pipeline-Ruby-Go",
      "kind": "composition",
      "status": "dry-run",
      "validation": "json-output",
      "platforms": [
        "macos"
      ],
      "requires": [
        "go",
        "op",
        "ruby",
        "bundle"
      ]
    },
    {
      "name": "charon-pipeline-rust-go",
      "path": "recipes/composition/pipeline/charon-pipeline-rust-go",
      "family_name": "Composition-Pipeline-Rust-Go",
      "display_family": "Composition-Pipeline-Rust-Go",
      "display_name": "Composition-Pipeline-Rust-Go",
      "kind": "composition",
      "status": "dry-run",
      "validation": "json-output",
      "platforms": [
        "macos"
      ],
      "requires": [
        "go",
        "op",
        "cargo"
      ]
    },
    {
      "name": "charon-pipeline-swift-go",
      "path": "recipes/composition/pipeline/charon-pipeline-swift-go",
      "family_name": "Composition-Pipeline-Swift-Go",
      "display_family": "Composition-Pipeline-Swift-Go",
      "display_name": "Composition-Pipeline-Swift-Go",
      "kind": "composition",
      "status": "dry-run",
      "validation": "json-output",
      "platforms": [
        "macos"
      ],
      "requires": [
        "go",
        "op",
        "swift",
        "xcodebuild"
      ]
    }
  ]
}
